LICENSE
MANIFEST.in
README.md
README.txt
setup.py
seqreppy/__init__.py
seqreppy/config.py
seqreppy.egg-info/PKG-INFO
seqreppy.egg-info/SOURCES.txt
seqreppy.egg-info/dependency_links.txt
seqreppy.egg-info/top_level.txt
seqreppy/gsp/__init__.py
seqreppy/gsp/gsp.py
seqreppy/sp/__init__.py
seqreppy/sp/sp.py
seqreppy/view/__init__.py
seqreppy/view/mplconfig.py
seqreppy/view/view.py