Metadata-Version: 1.0
Name: seqreppy
Version: 1.0.2
Summary: Python library for numerical representations of genomic sequences
Home-page: https://github.com/ednilsonlomazi/seqreppy
Author: Ednilson Lomazi
Author-email: ednilson.lomazi.gt@gmail.com
License: BSD 3-Clause License
Platform: UNKNOWN
